odoo/addons/mrp_workorder_ref/README.rst
odoo/addons/mrp_workorder_ref/__init__.py
odoo/addons/mrp_workorder_ref/__manifest__.py
odoo/addons/mrp_workorder_ref/i18n/mrp_workorder_ref.pot
odoo/addons/mrp_workorder_ref/models/__init__.py
odoo/addons/mrp_workorder_ref/models/mrp_production.py
odoo/addons/mrp_workorder_ref/models/mrp_routing_workcenter.py
odoo/addons/mrp_workorder_ref/models/mrp_workorder.py
odoo/addons/mrp_workorder_ref/readme/CONTRIBUTORS.rst
odoo/addons/mrp_workorder_ref/readme/DESCRIPTION.rst
odoo/addons/mrp_workorder_ref/static/description/icon.png
odoo/addons/mrp_workorder_ref/static/description/index.html
odoo/addons/mrp_workorder_ref/tests/__init__.py
odoo/addons/mrp_workorder_ref/tests/test_workorder_ref.py
odoo/addons/mrp_workorder_ref/views/mrp_routing_workcenter.xml
odoo/addons/mrp_workorder_ref/views/mrp_workorder.xml
odoo_addon_mrp_workorder_ref-15.0.1.0.0.2.dist-info/METADATA
odoo_addon_mrp_workorder_ref-15.0.1.0.0.2.dist-info/WHEEL
odoo_addon_mrp_workorder_ref-15.0.1.0.0.2.dist-info/top_level.txt
odoo_addon_mrp_workorder_ref-15.0.1.0.0.2.dist-info/RECORD
